MANIFEST.in
README.rst
setup.cfg
setup.py
versioneer.py
phildb_client/__init__.py
phildb_client/_version.py
phildb_client/client.py
phildb_client.egg-info/PKG-INFO
phildb_client.egg-info/SOURCES.txt
phildb_client.egg-info/dependency_links.txt
phildb_client.egg-info/pbr.json
phildb_client.egg-info/requires.txt
phildb_client.egg-info/top_level.txt